<?xml version="1.0" encoding="UTF-8" ?>
<!DOCTYPE tiles-definitions PUBLIC
"-//Apache Software Foundation//DTD Tiles Configuration 2.0//EN"
"http://tiles.apache.org/dtds/tiles-config_2_0.dtd">
<tiles-definitions>
   <definition name="baseLayout"  template="/WEB-INF/views/common/layout.jsp">
      <put-attribute name="title" value="" />
      <put-attribute name="header" value="/WEB-INF/views/common/header.jsp" />
      <put-attribute name="body" value="" />
      <put-attribute name="footer" value="/WEB-INF/views/common/footer.jsp" />
   </definition>
   <definition name="mypageLayout"  template="/WEB-INF/views/common/mypageLayout.jsp">
      <put-attribute name="title" value="" />
      <put-attribute name="header" value="/WEB-INF/views/common/header.jsp" />
      <put-attribute name="side" value="/WEB-INF/views/common/side.jsp" />
      <put-attribute name="body" value="" />
      <put-attribute name="footer" value="/WEB-INF/views/common/footer.jsp" />
   </definition>
   
   <definition name="adminLayout"  template="/WEB-INF/views/common/admin/adminLayout.jsp">
      <put-attribute name="title" value="" />
      <put-attribute name="header" value="/WEB-INF/views/common/admin/header.jsp" />
      <put-attribute name="side" value="/WEB-INF/views/common/admin/side.jsp" />
      <put-attribute name="body" value="" />
      <put-attribute name="footer" value="/WEB-INF/views/common/admin/footer.jsp" />
   </definition>

	<!-- 관리자 START -->
	<!-- 관리자메인페이지 -->
   <definition name="adminMain" extends="adminLayout">
      <put-attribute name="title" value="메인페이지" />
       <put-attribute name="body" value="" />
   </definition>

   <definition name="p001_d006_search" extends="adminLayout">
      <put-attribute name="title" value="메인페이지" />
       <put-attribute name="body" value="/WEB-INF/views/member/p001_d006_search.jsp" />
   </definition>
   <!-- 관리자페이지 END -->
   
	<!-- 메인페이지 -->
   <definition name="main" extends="baseLayout">
      <put-attribute name="title" value="관리자메인페이지" />
       <put-attribute name="body" value="/WEB-INF/views/root/p001_d001_init.jsp" />
   </definition>
   
	<!-- 비밀번호찾기 -->
   <definition name="p001_d003_init" extends="baseLayout">
      <put-attribute name="title" value="메인페이지" />
       <put-attribute name="body" value="/WEB-INF/views/member/p001_d003_init.jsp" />
   </definition>

   <!-- 같이먹기 메인 -->
   <definition name="eatMain" extends="baseLayout">
      <put-attribute name="title" value="메인페이지" />
       <put-attribute name="body" value="/WEB-INF/views/and/p001_d001_eatMain.jsp" />
   </definition> 
   <!-- 같이먹기 리스트 -->
   <definition name="andone_eat" extends="baseLayout">
      <put-attribute name="title" value="메인페이지" />
       <put-attribute name="body" value="/WEB-INF/views/and/p001_d001_listAndOne_eat.jsp" />
   </definition>
   <!-- 같이하기 리스트 -->
   <definition name="andone_do" extends="baseLayout">
      <put-attribute name="title" value="메인페이지" />
       <put-attribute name="body" value="/WEB-INF/views/and/p001_d001_listAndOne_do.jsp" />
   </definition>
   <!-- 같이사기 리스트 -->
   <definition name="andone_buy" extends="baseLayout">
      <put-attribute name="title" value="메인페이지" />
       <put-attribute name="body" value="/WEB-INF/views/and/p001_d001_listAndOne_buy.jsp" />
   </definition>

   <!-- 지역업체 페이지 -->
   <definition name="localShopMain" extends="baseLayout">
      <put-attribute name="title" value="지역업체 메인페이지" />
      <put-attribute name="body" value="/WEB-INF/views/shop/p002_d001_localShopMain.jsp" />
   </definition>
   
   <definition name="localShopSearch" extends="baseLayout">
      <put-attribute name="title" value="지역업체 검색결과" />
      <put-attribute name="body" value="/WEB-INF/views/shop/p002_d001_localShopSearch.jsp" />
   </definition>
   
   <definition name="localShopDetail" extends="baseLayout">
      <put-attribute name="title" value="지역업체 상세정보" />
      <put-attribute name="body" value="/WEB-INF/views/shop/p002_d001_localShopDetail.jsp" />
   </definition>
   
   <definition name="writeShopReview" extends="baseLayout">
      <put-attribute name="title" value="지역업체 리뷰작성" />
      <put-attribute name="body" value="/WEB-INF/views/shop/p003_d001_writeShopReview.jsp" />
   </definition>
   
   <definition name="modifyShopReview" extends="baseLayout">
      <put-attribute name="title" value="지역업체 리뷰수정" />
      <put-attribute name="body" value="/WEB-INF/views/shop/p003_d001_modifyShopReview.jsp" />
   </definition>
   
    <definition name="fileTest" extends="baseLayout">
      <put-attribute name="title" value="파일 업로드 테스트" />
      <put-attribute name="body" value="/WEB-INF/views/shop/fileTest.jsp" />
   </definition>
   
   <definition name="viewTest" extends="baseLayout">
      <put-attribute name="title" value="파일 출력 테스트" />
      <put-attribute name="body" value="/WEB-INF/views/shop/viewTest.jsp" />
   </definition>
   
	<!-- 비밀번호찾기 -->
   <definition name="p001_d003_init" extends="baseLayout">
      <put-attribute name="title" value="비밀번호 찾기" />
       <put-attribute name="body" value="/WEB-INF/views/member/p001_d003_init.jsp" />
   </definition>
	<!-- 비밀번호찾기 전송완료 -->
   <definition name="p001_d003_search" extends="baseLayout">
      <put-attribute name="title" value="비밀번호 찾기" />
       <put-attribute name="body" value="/WEB-INF/views/member/p001_d003_search.jsp" />
   </definition>
   
	<!-- 회원약관 -->
   <definition name="p001_d001_init" extends="baseLayout">
      <put-attribute name="title" value="회원약관" />
       <put-attribute name="body" value="/WEB-INF/views/member/p001_d001_init.jsp" />
   </definition>
   <!-- 가입폼 -->
   <definition name="p001_d001_insert" extends="baseLayout">
      <put-attribute name="title" value="회원약관" />
       <put-attribute name="body" value="/WEB-INF/views/member/p001_d001_insert.jsp" />
   </definition>
   <!-- 가입완료 -->
   <definition name="p001_d001_insert_sub01" extends="baseLayout">
      <put-attribute name="title" value="회원약관" />
       <put-attribute name="body" value="/WEB-INF/views/member/p001_d001_insert_sub01.jsp" />
   </definition>
   
   
   <!-- 마이페이지 -->
	<definition name="mypage" extends="mypageLayout">
		<put-attribute name="title" value="마이페이지"/>
		<put-attribute name="body" value="/WEB-INF/views/member/p001_init.jsp"/>
	</definition>
	
	<!-- 회원정보조회 -->
	<definition name="p001_d005_update" extends="mypageLayout">
		<put-attribute name="title" value="내 정보 변경"/>
		<put-attribute name="body" value="/WEB-INF/views/member/p001_d005_update.jsp"/>
	</definition>
	
	<!-- 소모임 메인-->
	<definition name="clubMain"  template="/WEB-INF/views/common/layout.jsp">
      <put-attribute name="title" value="소모임 메인" />
      <put-attribute name="header" value="/WEB-INF/views/common/header.jsp" />
      <put-attribute name="body" value="/WEB-INF/views/club/p001/p001_d001_clubMain.jsp" />
      <put-attribute name="footer" value="/WEB-INF/views/common/footer.jsp" />
   </definition>
	<!-- 소모임 상세페이지-->
	<definition name="detailClub"  template="/WEB-INF/views/common/layout.jsp">
      <put-attribute name="title" value="소모임 상세" />
      <put-attribute name="header" value="/WEB-INF/views/common/header.jsp" />
      <put-attribute name="body" value="/WEB-INF/views/club/p001/p001_d001_detailClub.jsp" />
      <put-attribute name="footer" value="/WEB-INF/views/common/footer.jsp" />
   </definition>
   
	<!-- 소모임 검색결과-->
   <definition name="searchList"  template="/WEB-INF/views/common/layout.jsp">
      <put-attribute name="title" value="소모임 검색결과" />
      <put-attribute name="header" value="/WEB-INF/views/common/header.jsp" />
      <put-attribute name="body" value="/WEB-INF/views/club/p001/p001_d001_search.jsp" />
      <put-attribute name="footer" value="/WEB-INF/views/common/footer.jsp" />
   </definition>
   
	<!-- 소모임 만들기-->
   <definition name="createClub"  template="/WEB-INF/views/common/layout.jsp">
      <put-attribute name="title" value="소모임 만들기" />
      <put-attribute name="header" value="/WEB-INF/views/common/header.jsp" />
      <put-attribute name="body" value="/WEB-INF/views/club/p002/p002_d001_insert.jsp" />
      <put-attribute name="footer" value="/WEB-INF/views/common/footer.jsp" />
   </definition>
   
   <!-- 소모임  게시글 쓰기-->
   <definition name="writeArticleForm"  template="/WEB-INF/views/common/layout.jsp">
      <put-attribute name="title" value="소모임 게시글 쓰기" />
      <put-attribute name="header" value="/WEB-INF/views/common/header.jsp" />
      <put-attribute name="body" value="/WEB-INF/views/club/p003/p003_d001_insert.jsp" />
      <put-attribute name="footer" value="/WEB-INF/views/common/footer.jsp" />
   </definition>
   
   <!-- 소모임  게시글 수정 페이지-->
   <definition name="editArticle"  template="/WEB-INF/views/common/layout.jsp">
      <put-attribute name="title" value="소모임 게시글 쓰기" />
      <put-attribute name="header" value="/WEB-INF/views/common/header.jsp" />
      <put-attribute name="body" value="/WEB-INF/views/club/p003/p003_d001_update.jsp" />
      <put-attribute name="footer" value="/WEB-INF/views/common/footer.jsp" />
   </definition>
   
	<definition name="p001_d005_init" extends="mypageLayout">
		<put-attribute name="title" value="내 정보 변경"/>
		<put-attribute name="body" value="/WEB-INF/views/member/p001_d005_init.jsp"/>
	</definition>
	<!-- 회원탈퇴 -->
	<definition name="p001_d004_init" extends="mypageLayout">
		<put-attribute name="title" value="내 정보 변경"/>
		<put-attribute name="body" value="/WEB-INF/views/member/p001_d004_init.jsp"/>
	</definition>

</tiles-definitions>
